MANIFEST.in
setup.py
AutoHDL.egg-info/PKG-INFO
AutoHDL.egg-info/SOURCES.txt
AutoHDL.egg-info/dependency_links.txt
AutoHDL.egg-info/requires.txt
AutoHDL.egg-info/top_level.txt
autohdl/__init__.py
autohdl/aldec.py
autohdl/aldec_run.py
autohdl/build.py
autohdl/dcs_channel.py
autohdl/deploy.py
autohdl/distribute_setup.py
autohdl/documentation.py
autohdl/git.py
autohdl/hdl.bat
autohdl/hdl.py
autohdl/hdlGlobals.py
autohdl/hdlLogger.py
autohdl/hdlManager.py
autohdl/install.py
autohdl/instance.py
autohdl/log_server.py
autohdl/packetdcs.py
autohdl/pkg_info.py
autohdl/procHandler.py
autohdl/progressBar.py
autohdl/publisher.py
autohdl/structure.py
autohdl/synplify.py
autohdl/template_avhdl_adf.py
autohdl/toolchain.py
autohdl/utils.py
autohdl/webdav.py
autohdl/xilinx.py
autohdl/xilinx_env.py
autohdl/data/__init__.py
autohdl/data/build.yaml
autohdl/data/kungfu.py
autohdl/data/run_avhdl.bat
autohdl/data/template_aldec_adf
autohdl/data/template_synplify_prj
autohdl/data/version.json
autohdl/doc/__init__.py
autohdl/doc/conf.py
autohdl/doc/_build/html/.buildinfo
autohdl/doc/_build/html/buildYaml.html
autohdl/doc/_build/html/genindex.html
autohdl/doc/_build/html/git.html
autohdl/doc/_build/html/index.html
autohdl/doc/_build/html/newDesign.html
autohdl/doc/_build/html/objects.inv
autohdl/doc/_build/html/search.html
autohdl/doc/_build/html/searchindex.js
autohdl/doc/_build/html/_sources/buildYaml.txt
autohdl/doc/_build/html/_sources/git.txt
autohdl/doc/_build/html/_sources/index.txt
autohdl/doc/_build/html/_sources/newDesign.txt
autohdl/doc/_build/html/_static/ajax-loader.gif
autohdl/doc/_build/html/_static/basic.css
autohdl/doc/_build/html/_static/comment-bright.png
autohdl/doc/_build/html/_static/comment-close.png
autohdl/doc/_build/html/_static/comment.png
autohdl/doc/_build/html/_static/default.css
autohdl/doc/_build/html/_static/doctools.js
autohdl/doc/_build/html/_static/down-pressed.png
autohdl/doc/_build/html/_static/down.png
autohdl/doc/_build/html/_static/file.png
autohdl/doc/_build/html/_static/jquery.js
autohdl/doc/_build/html/_static/minus.png
autohdl/doc/_build/html/_static/plus.png
