Metadata-Version: 1.1
Name: AutoHDL
Version: 2.7.982
Summary: Automatization Utilities for HDL projects
Home-page: UNKNOWN
Author: Maxim Golokhov
Author-email: hexwer@gmail.com
License: UNKNOWN
Platform: win32
Classifier: Programming Language :: Python :: 3.4
